pulsedive/__init__.py
pulsedive/client.py
pulsedive/exceptions.py
pulsedive/utils.py
pulsedive-0.1.0.dist-info/LICENSE
pulsedive-0.1.0.dist-info/METADATA
pulsedive-0.1.0.dist-info/WHEEL
pulsedive-0.1.0.dist-info/top_level.txt
pulsedive-0.1.0.dist-info/RECORD
