Metadata-Version: 2.1
Name: pulsedive
Version: 0.1.0
Summary: Python client for Pulsedive API
Home-page: https://github.com/pberba/pulsedive-py
Author: Pepe Berba
Author-email: jdpberba@gmail.com
License: MIT License
Platform: UNKNOWN
Classifier: Development Status :: 5 - Production/Stable
Classifier: License :: OSI Approved :: Apache Software License
Classifier: Intended Audience :: Developers
Classifier: Operating System :: OS Independent
Classifier: Programming Language :: Python
Classifier: Programming Language :: Python :: 2.7
Classifier: Programming Language :: Python :: 3.5
Classifier: Programming Language :: Python :: 3.6
Requires-Dist: requests
Provides-Extra: develop
Requires-Dist: pytest (>=3.3.0); extra == 'develop'
Requires-Dist: tox; extra == 'develop'
Requires-Dist: mock; extra == 'develop'
Requires-Dist: coverage; extra == 'develop'
Requires-Dist: sphinx; extra == 'develop'
Requires-Dist: sphinx-rtd-theme; extra == 'develop'
